<?xml version="1.0" encoding="utf-8" standalone="yes" ?>
<T3locallang>
	<meta type="array">
		<type>module</type>
		<description>Language labels for plugin &quot;tx_kesearch_pi1&quot;</description>
	</meta>
	<data type="array">
		<languageKey index="default" type="array">
			<label index="pi_title">Faceted Search</label>
			<label index="pi_plus_wiz_description">Show multiselection.</label>

			<label index="ff.main">General</label>
			<label index="ff.loadFlexformsFromOtherCE">Load flexforms config from this search box</label>
		</languageKey>
		<languageKey index="de" type="array">
			<label index="pi_title">Facettierte Suche</label>
			<label index="pi_plus_wiz_description">Mehrfachauswahl anzeigen.</label>

			<label index="ff.main">Konfiguration der Suchergebnisse</label>
			<label index="ff.loadFlexformsFromOtherCE">Flexform-Konfiguration von dieser Suchbox laden</label>
		</languageKey>
		<languageKey index="nl" type="array">
			<label index="pi_title">Facet Zoeken</label>
			<label index="pi_plus_wiz_description">Toon multiselectie</label>
			<label index="ff.main">Algemeen</label>
			<label index="ff.loadFlexformsFromOtherCE">Laad flexforms configuratie van dit zoekvak</label>
		</languageKey>
	</data>
</T3locallang>
